<?xml version="1.0" encoding="UTF-8"?>
<persistence version="2.0" xmlns="http://java.sun.com/xml/ns/persistence" xmlns:xsi="http://www.w3.org/2001/XMLSchema-instance" xsi:schemaLocation="http://java.sun.com/xml/ns/persistence http://java.sun.com/xml/ns/persistence/persistence_2_0.xsd">
  <persistence-unit name="KuwaibaToolsPersistenceUnit" transaction-type="RESOURCE_LOCAL">
    <provider>org.eclipse.persistence.jpa.PersistenceProvider</provider>
    <class>entity.config.User</class>
    <class>entity.config.UserGroup</class>
    <class>entity.connections.GenericConnection</class>
    <class>entity.connections.physical.ElectricalLink</class>
    <class>entity.connections.physical.GenericPhysicalConnection</class>
    <class>entity.connections.physical.OpticalLink</class>
    <class>entity.connections.physical.RadioLink</class>
    <class>entity.connections.physical.containers.GenericPhysicalContainer</class>
    <class>entity.connections.physical.containers.WireContainer</class>
    <class>entity.connections.physical.containers.WirelessContainer</class>
    <class>entity.core.AdministrativeItem</class>
    <class>entity.core.ConfigurationItem</class>
    <class>entity.core.DummyRoot</class>
    <class>entity.core.RootObject</class>
    <class>entity.core.ViewableObject</class>
    <class>entity.core.metamodel.AttributeMetadata</class>
    <class>entity.core.metamodel.ClassMetadata</class>
    <class>entity.core.metamodel.LockEntry</class>
    <class>entity.core.metamodel.PackageMetadata</class>
    <class>entity.equipment.applicationlayer.GenericApplicationElement</class>
    <class>entity.equipment.applicationlayer.Laptop</class>
    <class>entity.equipment.applicationlayer.Server</class>
    <class>entity.equipment.applicationlayer.WorkStation</class>
    <class>entity.equipment.containers.ACDistributionBoard</class>
    <class>entity.equipment.containers.BatteryBank</class>
    <class>entity.equipment.containers.DCDistributionBoard</class>
    <class>entity.equipment.containers.DDF</class>
    <class>entity.equipment.containers.FuseHolder</class>
    <class>entity.equipment.containers.GenericContainer</class>
    <class>entity.equipment.containers.GenericDistributionFrame</class>
    <class>entity.equipment.containers.ODF</class>
    <class>entity.equipment.containers.Rack</class>
    <class>entity.equipment.datalinklayer.GenericDataLinkElement</class>
    <class>entity.equipment.datalinklayer.PDHMux</class>
    <class>entity.equipment.datalinklayer.SDHMux</class>
    <class>entity.equipment.datalinklayer.Switch</class>
    <class>entity.equipment.datalinklayer.XDSLModem</class>
    <class>entity.equipment.misc.AirConditioning</class>
    <class>entity.equipment.misc.Slot</class>
    <class>entity.equipment.networklayer.GenericNetworkElement</class>
    <class>entity.equipment.networklayer.Router</class>
    <class>entity.equipment.physicallayer.DWDMMux</class>
    <class>entity.equipment.physicallayer.ExternalEquipment</class>
    <class>entity.equipment.physicallayer.GenericPhysicalElement</class>
    <class>entity.equipment.physicallayer.RadioShelf</class>
    <class>entity.equipment.physicallayer.Transceiver</class>
    <class>entity.equipment.physicallayer.parts.Antenna</class>
    <class>entity.equipment.physicallayer.parts.GenericPart</class>
    <class>entity.equipment.physicallayer.parts.SatelliteAntenna</class>
    <class>entity.equipment.physicallayer.parts.SpliceBox</class>
    <class>entity.equipment.physicallayer.parts.boards.DWDMBoard</class>
    <class>entity.equipment.physicallayer.parts.boards.GenericBoard</class>
    <class>entity.equipment.physicallayer.parts.boards.IPBoard</class>
    <class>entity.equipment.physicallayer.parts.boards.MixedBoard</class>
    <class>entity.equipment.physicallayer.parts.boards.RadioBoard</class>
    <class>entity.equipment.physicallayer.parts.boards.SDHBoard</class>
    <class>entity.equipment.physicallayer.parts.computers.GenericComputerPart</class>
    <class>entity.equipment.physicallayer.parts.computers.Keyboard</class>
    <class>entity.equipment.physicallayer.parts.computers.Monitor</class>
    <class>entity.equipment.physicallayer.parts.ports.ElectricalPort</class>
    <class>entity.equipment.physicallayer.parts.ports.GenericCommunicationsPort</class>
    <class>entity.equipment.physicallayer.parts.ports.GenericPort</class>
    <class>entity.equipment.physicallayer.parts.ports.OpticalPort</class>
    <class>entity.equipment.physicallayer.parts.ports.PowerPort</class>
    <class>entity.equipment.physicallayer.parts.ports.VirtualPort</class>
    <class>entity.equipment.physicallayer.power.DieselGenerator</class>
    <class>entity.equipment.physicallayer.power.GenericPowerElement</class>
    <class>entity.equipment.physicallayer.power.UPS</class>
    <class>entity.equipment.physicallayer.power.parts.Battery</class>
    <class>entity.equipment.physicallayer.power.parts.Breaker</class>
    <class>entity.equipment.physicallayer.power.parts.Fuse</class>
    <class>entity.equipment.physicallayer.power.parts.GenericPowerPart</class>
    <class>entity.equipment.physicallayer.power.parts.Rectifier</class>
    <class>entity.location.Building</class>
    <class>entity.location.City</class>
    <class>entity.location.Continent</class>
    <class>entity.location.Country</class>
    <class>entity.location.Facility</class>
    <class>entity.location.Floor</class>
    <class>entity.location.GenericLocation</class>
    <class>entity.location.GenericPhysicalNode</class>
    <class>entity.location.Room</class>
    <class>entity.location.Shelter</class>
    <class>entity.location.StateObject</class>
    <class>entity.location.Tower</class>
    <class>entity.location.Warehouse</class>
    <class>entity.multiple.GenericObjectList</class>
    <class>entity.multiple.bandwidths.GenericRate</class>
    <class>entity.multiple.bandwidths.IPRate</class>
    <class>entity.multiple.bandwidths.SDHRate</class>
    <class>entity.multiple.companies.CorporativeCustomer</class>
    <class>entity.multiple.companies.EquipmentProvider</class>
    <class>entity.multiple.companies.GenericCompany</class>
    <class>entity.multiple.companies.LocationOwner</class>
    <class>entity.multiple.companies.ServiceProvider</class>
    <class>entity.multiple.companies.Vendor</class>
    <class>entity.multiple.misc.EnvironmentalCondition</class>
    <class>entity.multiple.people.Employee</class>
    <class>entity.multiple.people.ExternalSupportStaff</class>
    <class>entity.multiple.people.GenericPerson</class>
    <class>entity.multiple.people.HomeCustomer</class>
    <class>entity.multiple.states.GenericState</class>
    <class>entity.multiple.states.OperationalState</class>
    <class>entity.multiple.states.StructuralState</class>
    <class>entity.multiple.systems.OperatingSystem</class>
    <class>entity.multiple.types.containers.PhysicalContainerType</class>
    <class>entity.multiple.types.links.ElectricalLinkType</class>
    <class>entity.multiple.types.links.GenericPhysicalLinkType</class>
    <class>entity.multiple.types.links.OpticalLinkType</class>
    <class>entity.multiple.types.links.WireContainerType</class>
    <class>entity.multiple.types.links.WirelessContainerType</class>
    <class>entity.multiple.types.links.WirelessLinkType</class>
    <class>entity.multiple.types.parts.AntennaType</class>
    <class>entity.multiple.types.parts.CommunicationsPortType</class>
    <class>entity.multiple.types.parts.PowerPortType</class>
    <class>entity.multiple.types.parts.TowerType</class>
    <class>entity.qos.OLA</class>
    <class>entity.qos.SLA</class>
    <class>entity.qos.services.GenericCorporativeService</class>
    <class>entity.qos.services.GenericHomeService</class>
    <class>entity.qos.services.GenericService</class>
    <class>entity.qos.services.IPService</class>
    <class>entity.qos.services.SDHService</class>
    <class>entity.qos.services.VoiceService</class>
    <class>entity.relations.GenericRelation</class>
    <class>entity.session.ClientDetail</class>
    <class>entity.session.UserSession</class>
    <class>entity.views.ClassView</class>
    <class>entity.views.DefaultView</class>
    <class>entity.views.GenericView</class>
    <class>entity.views.RackView</class>
    <properties>
      <property name="eclipselink.cache.shared.default" value="false"/>
      <property name="eclipselink.ddl-generation" value="none"/>
      <property name="javax.persistence.jdbc.password" value="kuwaiba"/>
      <property name="javax.persistence.jdbc.user" value="kuwaibadbuser"/>
      <property name="javax.persistence.jdbc.url" value="jdbc:postgresql://localhost:5432/kuwaibadb"/>
      <property name="javax.persistence.jdbc.driver" value="org.postgresql.Driver"/>
    </properties>
  </persistence-unit>
</persistence>
